{
	"type": {
		"name": "coppertones:default",
		"has_skylight": true,
		"fixed_time": 6000,
		"ambient_light": 0.1,
		"has_ceiling": false,
		"logical_height": 256,
		"natural": true,
		"ultrawarm": false,
		"shrunk": false,
		"piglin_safe": true,
		"has_raids": false,
		"bed_works": true,
		"respawn_anchor_works": true,
		"infiniburn": "minecraft:infiniburn_overworld"
	},
	"generator": {
		"type": "minecraft:flat",
		"settings": {
			"layers": [
				{
					"block": "minecraft:bedrock",
					"height": 1
				},
				{
					"block": "minecraft:dirt",
					"height": 62
				},
				{
					"block": "minecraft:grass_block",
					"height": 1
				}
			],
			"biome": "coppertones:omni_forest",
			"lakes": false,
			"features": true,
			"structures": {
				"structures": {}
			}
		}
	}
}